README.md
setup.py
tests/__init__.py
tests/test_base.py
tests/utils.py
tests/companies/__init__.py
tests/companies/test_search.py
tests/report/__init__.py
tests/report/test_get.py
tests/verification_requests/__init__.py
tests/verification_requests/test_create.py
tests/verification_requests/test_list.py
tests/verification_requests/test_retrieve.py
truework/__init__.py
truework/address.py
truework/base.py
truework/company.py
truework/earnings.py
truework/employee.py
truework/employer.py
truework/position.py
truework/price.py
truework/report.py
truework/salary.py
truework/turnaround_time.py
truework/verification_request.py
truework/version.py
truework.egg-info/PKG-INFO
truework.egg-info/SOURCES.txt
truework.egg-info/dependency_links.txt
truework.egg-info/requires.txt
truework.egg-info/top_level.txt