Metadata-Version: 2.1
Name: truework
Version: 0.0.1
Summary: An SDK to use the Truework API
Home-page: https://github.com/truework/truework-sdk-python
Author: Truework
Author-email: python-sdk@truework.com
License: UNKNOWN
Platform: UNKNOWN
Classifier: Programming Language :: Python :: 2.7
Classifier: Programming Language :: Python :: 3.6
Classifier: License :: OSI Approved :: MIT License
Classifier: Operating System :: OS Independent
Requires-Python: >=2.7, <4
